Metadata-Version: 1.0
Name: speech-synthesis
Version: 1.3
Summary: 使用百度AI语音合成
Home-page: UNKNOWN
Author: haxif
Author-email: 1160370538@qq.com
License: UNKNOWN
Platform: any
